BankDetails/__init__.py
BankDetails/bank.py
BankDetails/bank_day_details.py
BankDetails/bank_test.py
BankDetails/config.py
OtherWare/__init__.py
OtherWare/metadata.py
OtherWare/utility.py
rdCustomer/DatabaseOperations.py
rdCustomer/Metadata.py
rdCustomer/Utility.py
rdCustomer/__init__.py
rdCustomer/customerOAInterface.py
rdSaleOrder/EcsInterface.py
rdSaleOrder/__init__.py
rdSaleOrder/mainModel.py
rdSaleOrder/metadata.py
rdSaleOrder/operation.py
rdSaleOrder/utility.py
rdSupplier/DatabaseOperations.py
rdSupplier/Metadata.py
rdSupplier/SupplierOAInterface.py
rdSupplier/Utility.py
rdSupplier/__init__.py
bank_details-1.3.1.dist-info/METADATA
bank_details-1.3.1.dist-info/WHEEL
bank_details-1.3.1.dist-info/top_level.txt
bank_details-1.3.1.dist-info/RECORD
