Metadata-Version: 2.1
Name: bank-details
Version: 1.3.1
Summary: test for zip
Home-page: UNKNOWN
Author: yb
Author-email: 623374149@qq.com
License: UNKNOWN
Platform: UNKNOWN
